plotly_express/__init__.py
plotly_express-0.4.0.dist-info/METADATA
plotly_express-0.4.0.dist-info/RECORD
plotly_express-0.4.0.dist-info/WHEEL
plotly_express-0.4.0.dist-info/top_level.txt
