Metadata-Version: 2.1
Name: plotly_express
Version: 0.4.0
Summary: Plotly Express - a high level wrapper for Plotly.py
Home-page: https://plotly.express/
Author: Nicolas Kruchten
Author-email: nicolas@plot.ly
License: MIT
Project-URL: Github, https://github.com/plotly/plotly_express/
Platform: UNKNOWN
Classifier: Development Status :: 5 - Production/Stable
Classifier: Topic :: Scientific/Engineering :: Visualization
Classifier: License :: OSI Approved :: MIT License
